[{"日期": "2024-01-26 00:00:00", "股票代码": "300477", "开盘": 3.43, "收盘": 3.35, "最高": 3.46, "最低": 3.11, "周成交量": 680298, "成交额": 222790431.0, "振幅": 10.14, "涨跌幅": -2.9, "涨跌额": -0.1, "换手率": 7.27}, {"日期": "2024-02-02 00:00:00", "股票代码": "300477", "开盘": 3.36, "收盘": 2.52, "最高": 3.36, "最低": 2.4, "周成交量": 948482, "成交额": 269101206.0, "振幅": 28.66, "涨跌幅": -24.78, "涨跌额": -0.83, "换手率": 10.14}, {"日期": "2024-02-08 00:00:00", "股票代码": "300477", "开盘": 2.51, "收盘": 2.16, "最高": 2.51, "最低": 1.93, "周成交量": 1471985, "成交额": 305648858.0, "振幅": 23.02, "涨跌幅": -14.29, "涨跌额": -0.36, "换手率": 15.74}, {"日期": "2024-02-23 00:00:00", "股票代码": "300477", "开盘": 2.16, "收盘": 2.7, "最高": 2.71, "最低": 2.16, "周成交量": 1326154, "成交额": 323342081.0, "振幅": 25.46, "涨跌幅": 25.0, "涨跌额": 0.54, "换手率": 14.18}, {"日期": "2024-03-01 00:00:00", "股票代码": "300477", "开盘": 2.72, "收盘": 2.78, "最高": 2.97, "最低": 2.56, "周成交量": 1363014, "成交额": 376377751.0, "振幅": 15.19, "涨跌幅": 2.96, "涨跌额": 0.08, "换手率": 14.57}, {"日期": "2024-03-08 00:00:00", "股票代码": "300477", "开盘": 2.76, "收盘": 2.67, "最高": 2.82, "最低": 2.61, "周成交量": 743548, "成交额": 199766100.0, "振幅": 7.55, "涨跌幅": -3.96, "涨跌额": -0.11, "换手率": 7.95}, {"日期": "2024-03-15 00:00:00", "股票代码": "300477", "开盘": 2.67, "收盘": 2.89, "最高": 2.91, "最低": 2.65, "周成交量": 1112824, "成交额": 312620701.0, "振幅": 9.74, "涨跌幅": 8.24, "涨跌额": 0.22, "换手率": 11.9}, {"日期": "2024-03-22 00:00:00", "股票代码": "300477", "开盘": 2.89, "收盘": 2.88, "最高": 3.03, "最低": 2.85, "周成交量": 985005, "成交额": 288624642.0, "振幅": 6.23, "涨跌幅": -0.35, "涨跌额": -0.01, "换手率": 10.53}, {"日期": "2024-03-29 00:00:00", "股票代码": "300477", "开盘": 2.84, "收盘": 2.75, "最高": 2.88, "最低": 2.66, "周成交量": 697149, "成交额": 192976150.0, "振幅": 7.64, "涨跌幅": -4.51, "涨跌额": -0.13, "换手率": 7.45}, {"日期": "2024-04-03 00:00:00", "股票代码": "300477", "开盘": 2.77, "收盘": 3.89, "最高": 4.27, "最低": 2.76, "周成交量": 4471155, "成交额": 1672454698.0, "振幅": 54.91, "涨跌幅": 41.45, "涨跌额": 1.14, "换手率": 47.8}, {"日期": "2024-04-12 00:00:00", "股票代码": "300477", "开盘": 3.72, "收盘": 3.29, "最高": 4.05, "最低": 3.24, "周成交量": 5535414, "成交额": 2012206389.0, "振幅": 20.82, "涨跌幅": -15.42, "涨跌额": -0.6, "换手率": 59.17}, {"日期": "2024-04-19 00:00:00", "股票代码": "300477", "开盘": 3.15, "收盘": 3.02, "最高": 3.44, "最低": 2.4, "周成交量": 4372032, "成交额": 1269525665.0, "振幅": 31.61, "涨跌幅": -8.21, "涨跌额": -0.27, "换手率": 46.74}, {"日期": "2024-04-26 00:00:00", "股票代码": "300477", "开盘": 2.98, "收盘": 2.79, "最高": 3.07, "最低": 2.69, "周成交量": 2363821, "成交额": 670575303.0, "振幅": 12.58, "涨跌幅": -7.62, "涨跌额": -0.23, "换手率": 25.27}, {"日期": "2024-04-30 00:00:00", "股票代码": "300477", "开盘": 2.74, "收盘": 2.91, "最高": 3.07, "最低": 2.73, "周成交量": 1258730, "成交额": 370574458.0, "振幅": 12.19, "涨跌幅": 4.3, "涨跌额": 0.12, "换手率": 13.46}, {"日期": "2024-05-10 00:00:00", "股票代码": "300477", "开盘": 2.96, "收盘": 3.54, "最高": 3.96, "最低": 2.86, "周成交量": 4698121, "成交额": 1604971284.0, "振幅": 37.8, "涨跌幅": 21.65, "涨跌额": 0.63, "换手率": 50.22}, {"日期": "2024-05-17 00:00:00", "股票代码": "300477", "开盘": 3.48, "收盘": 3.24, "最高": 3.75, "最低": 3.16, "周成交量": 4692914, "成交额": 1593133316.0, "振幅": 16.67, "涨跌幅": -8.47, "涨跌额": -0.3, "换手率": 50.17}, {"日期": "2024-05-24 00:00:00", "股票代码": "300477", "开盘": 3.23, "收盘": 3.12, "最高": 3.58, "最低": 3.09, "周成交量": 3249002, "成交额": 1068403077.0, "振幅": 15.12, "涨跌幅": -3.7, "涨跌额": -0.12, "换手率": 34.73}, {"日期": "2024-05-31 00:00:00", "股票代码": "300477", "开盘": 3.13, "收盘": 2.91, "最高": 3.22, "最低": 2.82, "周成交量": 1944337, "成交额": 587301439.0, "振幅": 12.82, "涨跌幅": -6.73, "涨跌额": -0.21, "换手率": 20.79}, {"日期": "2024-06-07 00:00:00", "股票代码": "300477", "开盘": 2.82, "收盘": 2.5, "最高": 2.82, "最低": 2.31, "周成交量": 1989891, "成交额": 510452507.0, "振幅": 17.53, "涨跌幅": -14.09, "涨跌额": -0.41, "换手率": 21.27}, {"日期": "2024-06-14 00:00:00", "股票代码": "300477", "开盘": 2.47, "收盘": 2.41, "最高": 2.56, "最低": 2.39, "周成交量": 1118413, "成交额": 274734181.0, "振幅": 6.8, "涨跌幅": -3.6, "涨跌额": -0.09, "换手率": 11.96}, {"日期": "2024-06-21 00:00:00", "股票代码": "300477", "开盘": 2.42, "收盘": 2.62, "最高": 2.95, "最低": 2.35, "周成交量": 2189453, "成交额": 567746221.0, "振幅": 24.9, "涨跌幅": 8.71, "涨跌额": 0.21, "换手率": 23.4}, {"日期": "2024-06-28 00:00:00", "股票代码": "300477", "开盘": 2.63, "收盘": 2.36, "最高": 2.64, "最低": 2.31, "周成交量": 1243305, "成交额": 300350554.0, "振幅": 12.6, "涨跌幅": -9.92, "涨跌额": -0.26, "换手率": 13.29}, {"日期": "2024-07-05 00:00:00", "股票代码": "300477", "开盘": 2.36, "收盘": 2.44, "最高": 2.68, "最低": 2.35, "周成交量": 1451846, "成交额": 358877948.0, "振幅": 13.98, "涨跌幅": 3.39, "涨跌额": 0.08, "换手率": 15.52}, {"日期": "2024-07-12 00:00:00", "股票代码": "300477", "开盘": 2.41, "收盘": 2.32, "最高": 2.57, "最低": 2.16, "周成交量": 1520955, "成交额": 355807754.0, "振幅": 16.8, "涨跌幅": -4.92, "涨跌额": -0.12, "换手率": 16.26}, {"日期": "2024-07-19 00:00:00", "股票代码": "300477", "开盘": 2.31, "收盘": 2.25, "最高": 2.37, "最低": 2.21, "周成交量": 839614, "成交额": 191891797.0, "振幅": 6.9, "涨跌幅": -3.02, "涨跌额": -0.07, "换手率": 8.98}, {"日期": "2024-07-26 00:00:00", "股票代码": "300477", "开盘": 2.25, "收盘": 2.27, "最高": 2.34, "最低": 2.18, "周成交量": 710598, "成交额": 160809711.0, "振幅": 7.11, "涨跌幅": 0.89, "涨跌额": 0.02, "换手率": 7.6}, {"日期": "2024-08-02 00:00:00", "股票代码": "300477", "开盘": 2.27, "收盘": 2.36, "最高": 2.45, "最低": 2.23, "周成交量": 1303161, "成交额": 308992151.0, "振幅": 9.69, "涨跌幅": 3.96, "涨跌额": 0.09, "换手率": 13.93}, {"日期": "2024-08-09 00:00:00", "股票代码": "300477", "开盘": 2.31, "收盘": 2.35, "最高": 2.43, "最低": 2.28, "周成交量": 998081, "成交额": 235113872.0, "振幅": 6.36, "涨跌幅": -0.42, "涨跌额": -0.01, "换手率": 10.67}, {"日期": "2024-08-16 00:00:00", "股票代码": "300477", "开盘": 2.33, "收盘": 2.41, "最高": 2.5, "最低": 2.25, "周成交量": 1323433, "成交额": 317129860.0, "振幅": 10.64, "涨跌幅": 2.55, "涨跌额": 0.06, "换手率": 14.15}, {"日期": "2024-08-23 00:00:00", "股票代码": "300477", "开盘": 2.4, "收盘": 2.38, "最高": 2.77, "最低": 2.32, "周成交量": 2929244, "成交额": 736752938.0, "振幅": 18.67, "涨跌幅": -1.24, "涨跌额": -0.03, "换手率": 31.31}, {"日期": "2024-08-30 00:00:00", "股票代码": "300477", "开盘": 2.35, "收盘": 2.37, "最高": 2.47, "最低": 2.19, "周成交量": 1499198, "成交额": 349044625.0, "振幅": 11.76, "涨跌幅": -0.42, "涨跌额": -0.01, "换手率": 16.03}, {"日期": "2024-09-06 00:00:00", "股票代码": "300477", "开盘": 2.4, "收盘": 2.3, "最高": 2.46, "最低": 2.29, "周成交量": 1231154, "成交额": 292438762.0, "振幅": 7.17, "涨跌幅": -2.95, "涨跌额": -0.07, "换手率": 13.16}, {"日期": "2024-09-13 00:00:00", "股票代码": "300477", "开盘": 2.28, "收盘": 2.35, "最高": 2.65, "最低": 2.28, "周成交量": 1679204, "成交额": 408945489.0, "振幅": 16.09, "涨跌幅": 2.17, "涨跌额": 0.05, "换手率": 17.95}, {"日期": "2024-09-20 00:00:00", "股票代码": "300477", "开盘": 2.34, "收盘": 2.34, "最高": 2.38, "最低": 2.26, "周成交量": 619851, "成交额": 144151224.0, "振幅": 5.11, "涨跌幅": -0.43, "涨跌额": -0.01, "换手率": 6.63}, {"日期": "2024-09-27 00:00:00", "股票代码": "300477", "开盘": 2.34, "收盘": 2.77, "最高": 2.88, "最低": 2.32, "周成交量": 2497147, "成交额": 640953579.0, "振幅": 23.93, "涨跌幅": 18.38, "涨跌额": 0.43, "换手率": 26.69}, {"日期": "2024-09-30 00:00:00", "股票代码": "300477", "开盘": 2.87, "收盘": 3.26, "最高": 3.26, "最低": 2.87, "周成交量": 1157273, "成交额": 354526124.0, "振幅": 14.08, "涨跌幅": 17.69, "涨跌额": 0.49, "换手率": 12.37}, {"日期": "2024-10-11 00:00:00", "股票代码": "300477", "开盘": 3.87, "收盘": 2.91, "最高": 3.9, "最低": 2.85, "周成交量": 3579733, "成交额": 1225548835.0, "振幅": 32.21, "涨跌幅": -10.74, "涨跌额": -0.35, "换手率": 38.27}, {"日期": "2024-10-18 00:00:00", "股票代码": "300477", "开盘": 2.92, "收盘": 3.05, "最高": 3.15, "最低": 2.84, "周成交量": 2160141, "成交额": 647881824.0, "振幅": 10.65, "涨跌幅": 4.81, "涨跌额": 0.14, "换手率": 23.09}, {"日期": "2024-10-25 00:00:00", "股票代码": "300477", "开盘": 3.07, "收盘": 3.31, "最高": 3.45, "最低": 3.05, "周成交量": 3197576, "成交额": 1034751970.0, "振幅": 13.11, "涨跌幅": 8.52, "涨跌额": 0.26, "换手率": 34.18}, {"日期": "2024-11-01 00:00:00", "股票代码": "300477", "开盘": 3.26, "收盘": 3.31, "最高": 3.64, "最低": 3.2, "周成交量": 3208091, "成交额": 1085148004.0, "振幅": 13.29, "涨跌幅": 0.0, "涨跌额": 0.0, "换手率": 34.29}, {"日期": "2024-11-08 00:00:00", "股票代码": "300477", "开盘": 3.26, "收盘": 3.68, "最高": 3.96, "最低": 3.16, "周成交量": 4398406, "成交额": 1565883987.0, "振幅": 24.17, "涨跌幅": 11.18, "涨跌额": 0.37, "换手率": 47.02}, {"日期": "2024-11-15 00:00:00", "股票代码": "300477", "开盘": 3.61, "收盘": 3.42, "最高": 3.76, "最低": 3.41, "周成交量": 2811953, "成交额": 1015757959.0, "振幅": 9.51, "涨跌幅": -7.07, "涨跌额": -0.26, "换手率": 30.06}, {"日期": "2024-11-22 00:00:00", "股票代码": "300477", "开盘": 3.42, "收盘": 3.4, "最高": 3.63, "最低": 3.16, "周成交量": 2205009, "成交额": 755853717.0, "振幅": 13.74, "涨跌幅": -0.58, "涨跌额": -0.02, "换手率": 23.57}, {"日期": "2024-11-29 00:00:00", "股票代码": "300477", "开盘": 3.39, "收盘": 3.5, "最高": 3.6, "最低": 3.26, "周成交量": 2265018, "成交额": 785527721.0, "振幅": 10.0, "涨跌幅": 2.94, "涨跌额": 0.1, "换手率": 24.21}, {"日期": "2024-12-06 00:00:00", "股票代码": "300477", "开盘": 3.5, "收盘": 3.86, "最高": 3.88, "最低": 3.48, "周成交量": 3836159, "成交额": 1427353865.0, "振幅": 11.43, "涨跌幅": 10.29, "涨跌额": 0.36, "换手率": 41.01}, {"日期": "2024-12-13 00:00:00", "股票代码": "300477", "开盘": 3.84, "收盘": 3.6, "最高": 3.91, "最低": 3.57, "周成交量": 2864993, "成交额": 1068166310.0, "振幅": 8.81, "涨跌幅": -6.74, "涨跌额": -0.26, "换手率": 30.63}, {"日期": "2024-12-20 00:00:00", "股票代码": "300477", "开盘": 3.59, "收盘": 3.32, "最高": 3.65, "最低": 3.18, "周成交量": 2118246, "成交额": 717210285.0, "振幅": 13.06, "涨跌幅": -7.78, "涨跌额": -0.28, "换手率": 22.64}, {"日期": "2024-12-27 00:00:00", "股票代码": "300477", "开盘": 3.32, "收盘": 3.05, "最高": 3.5, "最低": 2.86, "周成交量": 2196712, "成交额": 679121334.0, "振幅": 19.28, "涨跌幅": -8.13, "涨跌额": -0.27, "换手率": 23.48}, {"日期": "2025-01-03 00:00:00", "股票代码": "300477", "开盘": 3.02, "收盘": 2.84, "最高": 3.05, "最低": 2.75, "周成交量": 1294741, "成交额": 375098682.0, "振幅": 9.84, "涨跌幅": -6.89, "涨跌额": -0.21, "换手率": 13.84}, {"日期": "2025-01-10 00:00:00", "股票代码": "300477", "开盘": 2.79, "收盘": 2.68, "最高": 2.88, "最低": 2.63, "周成交量": 1127669, "成交额": 315234207.0, "振幅": 8.8, "涨跌幅": -5.63, "涨跌额": -0.16, "换手率": 12.05}, {"日期": "2025-01-17 00:00:00", "股票代码": "300477", "开盘": 2.64, "收盘": 2.81, "最高": 3.15, "最低": 2.58, "周成交量": 2034080, "成交额": 591171068.0, "振幅": 21.27, "涨跌幅": 4.85, "涨跌额": 0.13, "换手率": 21.74}, {"日期": "2025-01-24 00:00:00", "股票代码": "300477", "开盘": 2.83, "收盘": 2.7, "最高": 2.85, "最低": 2.65, "周成交量": 937630, "成交额": 257271712.0, "振幅": 7.12, "涨跌幅": -3.91, "涨跌额": -0.11, "换手率": 10.02}, {"日期": "2025-01-27 00:00:00", "股票代码": "300477", "开盘": 2.69, "收盘": 2.65, "最高": 2.73, "最低": 2.65, "周成交量": 154310, "成交额": 41472904.0, "振幅": 2.96, "涨跌幅": -1.85, "涨跌额": -0.05, "换手率": 1.65}, {"日期": "2025-02-07 00:00:00", "股票代码": "300477", "开盘": 2.69, "收盘": 2.84, "最高": 2.87, "最低": 2.67, "周成交量": 689117, "成交额": 191353321.0, "振幅": 7.55, "涨跌幅": 7.17, "涨跌额": 0.19, "换手率": 7.37}, {"日期": "2025-02-14 00:00:00", "股票代码": "300477", "开盘": 2.83, "收盘": 2.91, "最高": 2.96, "最低": 2.82, "周成交量": 1248855, "成交额": 360526712.0, "振幅": 4.93, "涨跌幅": 2.46, "涨跌额": 0.07, "换手率": 13.35}, {"日期": "2025-02-21 00:00:00", "股票代码": "300477", "开盘": 2.95, "收盘": 3.01, "最高": 3.09, "最低": 2.87, "周成交量": 2269440, "成交额": 673844328.0, "振幅": 7.56, "涨跌幅": 3.44, "涨跌额": 0.1, "换手率": 24.26}, {"日期": "2025-02-28 00:00:00", "股票代码": "300477", "开盘": 3.02, "收盘": 3.0, "最高": 3.24, "最低": 2.98, "周成交量": 2706139, "成交额": 847423485.0, "振幅": 8.64, "涨跌幅": -0.33, "涨跌额": -0.01, "换手率": 28.93}, {"日期": "2025-03-07 00:00:00", "股票代码": "300477", "开盘": 3.04, "收盘": 2.98, "最高": 3.32, "最低": 2.93, "周成交量": 2324371, "成交额": 712027098.0, "振幅": 13.0, "涨跌幅": -0.67, "涨跌额": -0.02, "换手率": 24.85}, {"日期": "2025-03-14 00:00:00", "股票代码": "300477", "开盘": 2.98, "收盘": 3.19, "最高": 3.38, "最低": 2.93, "周成交量": 3175386, "成交额": 995811090.0, "振幅": 15.1, "涨跌幅": 7.05, "涨跌额": 0.21, "换手率": 33.94}, {"日期": "2025-03-21 00:00:00", "股票代码": "300477", "开盘": 3.16, "收盘": 3.01, "最高": 3.21, "最低": 3.0, "周成交量": 1858951, "成交额": 579044375.0, "振幅": 6.58, "涨跌幅": -5.64, "涨跌额": -0.18, "换手率": 19.87}, {"日期": "2025-03-28 00:00:00", "股票代码": "300477", "开盘": 2.98, "收盘": 3.33, "最高": 3.82, "最低": 2.81, "周成交量": 7222714, "成交额": 2494514649.0, "振幅": 33.55, "涨跌幅": 10.63, "涨跌额": 0.32, "换手率": 77.21}, {"日期": "2025-04-03 00:00:00", "股票代码": "300477", "开盘": 3.27, "收盘": 3.02, "最高": 3.32, "最低": 2.99, "周成交量": 3292574, "成交额": 1031040192.0, "振幅": 9.91, "涨跌幅": -9.31, "涨跌额": -0.31, "换手率": 35.2}, {"日期": "2025-04-11 00:00:00", "股票代码": "300477", "开盘": 2.82, "收盘": 2.58, "最高": 2.82, "最低": 2.22, "周成交量": 3326479, "成交额": 841708136.0, "振幅": 19.87, "涨跌幅": -14.57, "涨跌额": -0.44, "换手率": 35.56}, {"日期": "2025-04-18 00:00:00", "股票代码": "300477", "开盘": 2.64, "收盘": 2.58, "最高": 2.82, "最低": 2.51, "周成交量": 2261729, "成交额": 598501741.0, "振幅": 12.02, "涨跌幅": 0.0, "涨跌额": 0.0, "换手率": 24.18}, {"日期": "2025-04-25 00:00:00", "股票代码": "300477", "开盘": 2.59, "收盘": 2.49, "最高": 2.63, "最低": 2.46, "周成交量": 1511514, "成交额": 385218399.0, "振幅": 6.59, "涨跌幅": -3.49, "涨跌额": -0.09, "换手率": 16.16}, {"日期": "2025-04-30 00:00:00", "股票代码": "300477", "开盘": 1.99, "收盘": 1.68, "最高": 1.99, "最低": 1.59, "周成交量": 1801880, "成交额": 305199502.0, "振幅": 16.06, "涨跌幅": -32.53, "涨跌额": -0.81, "换手率": 19.26}, {"日期": "2025-05-09 00:00:00", "股票代码": "300477", "开盘": 1.64, "收盘": 1.86, "最高": 1.95, "最低": 1.63, "周成交量": 2936804, "成交额": 521941079.0, "振幅": 19.05, "涨跌幅": 10.71, "涨跌额": 0.18, "换手率": 31.39}, {"日期": "2025-05-16 00:00:00", "股票代码": "300477", "开盘": 1.87, "收盘": 1.79, "最高": 1.93, "最低": 1.77, "周成交量": 2136589, "成交额": 393977997.0, "振幅": 8.6, "涨跌幅": -3.76, "涨跌额": -0.07, "换手率": 22.84}, {"日期": "2025-05-23 00:00:00", "股票代码": "300477", "开盘": 1.82, "收盘": 1.9, "最高": 2.06, "最低": 1.81, "周成交量": 2559590, "成交额": 498646804.0, "振幅": 13.97, "涨跌幅": 6.15, "涨跌额": 0.11, "换手率": 27.36}, {"日期": "2025-05-30 00:00:00", "股票代码": "300477", "开盘": 1.9, "收盘": 1.89, "最高": 1.98, "最低": 1.87, "周成交量": 1554505, "成交额": 299995580.0, "振幅": 5.79, "涨跌幅": -0.53, "涨跌额": -0.01, "换手率": 16.62}, {"日期": "2025-06-06 00:00:00", "股票代码": "300477", "开盘": 1.9, "收盘": 1.95, "最高": 1.98, "最低": 1.89, "周成交量": 1110903, "成交额": 215062908.0, "振幅": 4.76, "涨跌幅": 3.17, "涨跌额": 0.06, "换手率": 11.88}, {"日期": "2025-06-13 00:00:00", "股票代码": "300477", "开盘": 1.95, "收盘": 2.3, "最高": 2.34, "最低": 1.94, "周成交量": 3552407, "成交额": 759898971.0, "振幅": 20.51, "涨跌幅": 17.95, "涨跌额": 0.35, "换手率": 37.97}, {"日期": "2025-06-20 00:00:00", "股票代码": "300477", "开盘": 2.28, "收盘": 2.03, "最高": 2.33, "最低": 2.03, "周成交量": 2471227, "成交额": 532173245.0, "振幅": 13.04, "涨跌幅": -11.74, "涨跌额": -0.27, "换手率": 26.42}, {"日期": "2025-06-27 00:00:00", "股票代码": "300477", "开盘": 2.0, "收盘": 2.14, "最高": 2.19, "最低": 1.99, "周成交量": 1687788, "成交额": 358990617.0, "振幅": 9.85, "涨跌幅": 5.42, "涨跌额": 0.11, "换手率": 18.04}, {"日期": "2025-07-04 00:00:00", "股票代码": "300477", "开盘": 2.16, "收盘": 2.26, "最高": 2.45, "最低": 2.16, "周成交量": 2705806, "成交额": 622743705.0, "振幅": 13.55, "涨跌幅": 5.61, "涨跌额": 0.12, "换手率": 27.31}, {"日期": "2025-07-11 00:00:00", "股票代码": "300477", "开盘": 2.29, "收盘": 2.25, "最高": 2.32, "最低": 2.22, "周成交量": 1462806, "成交额": 330760663.0, "振幅": 4.42, "涨跌幅": -0.44, "涨跌额": -0.01, "换手率": 14.76}, {"日期": "2025-07-18 00:00:00", "股票代码": "300477", "开盘": 2.24, "收盘": 2.29, "最高": 2.32, "最低": 2.15, "周成交量": 1683017, "成交额": 377398429.0, "振幅": 7.56, "涨跌幅": 1.78, "涨跌额": 0.04, "换手率": 16.99}, {"日期": "2025-07-25 00:00:00", "股票代码": "300477", "开盘": 2.3, "收盘": 2.21, "最高": 2.33, "最低": 2.2, "周成交量": 1882235, "成交额": 425326533.0, "振幅": 5.68, "涨跌幅": -3.49, "涨跌额": -0.08, "换手率": 19.0}, {"日期": "2025-08-01 00:00:00", "股票代码": "300477", "开盘": 2.2, "收盘": 2.13, "最高": 2.23, "最低": 2.11, "周成交量": 1349784, "成交额": 290796416.0, "振幅": 5.43, "涨跌幅": -3.62, "涨跌额": -0.08, "换手率": 13.62}, {"日期": "2025-08-08 00:00:00", "股票代码": "300477", "开盘": 2.13, "收盘": 2.13, "最高": 2.19, "最低": 2.11, "周成交量": 1293505, "成交额": 277430480.0, "振幅": 3.76, "涨跌幅": 0.0, "涨跌额": 0.0, "换手率": 13.05}, {"日期": "2025-08-15 00:00:00", "股票代码": "300477", "开盘": 2.15, "收盘": 2.07, "最高": 2.17, "最低": 2.04, "周成交量": 1408606, "成交额": 297250089.0, "振幅": 6.1, "涨跌幅": -2.82, "涨跌额": -0.06, "换手率": 14.22}, {"日期": "2025-08-22 00:00:00", "股票代码": "300477", "开盘": 2.08, "收盘": 2.17, "最高": 2.24, "最低": 2.07, "周成交量": 1883414, "成交额": 404393964.0, "振幅": 8.21, "涨跌幅": 4.83, "涨跌额": 0.1, "换手率": 19.01}, {"日期": "2025-08-29 00:00:00", "股票代码": "300477", "开盘": 2.17, "收盘": 2.09, "最高": 2.28, "最低": 2.06, "周成交量": 2418965, "成交额": 525178242.0, "振幅": 10.14, "涨跌幅": -3.69, "涨跌额": -0.08, "换手率": 24.41}, {"日期": "2025-09-05 00:00:00", "股票代码": "300477", "开盘": 2.09, "收盘": 2.19, "最高": 2.25, "最低": 2.08, "周成交量": 2308190, "成交额": 499196228.0, "振幅": 8.13, "涨跌幅": 4.78, "涨跌额": 0.1, "换手率": 23.3}, {"日期": "2025-09-12 00:00:00", "股票代码": "300477", "开盘": 2.18, "收盘": 2.09, "最高": 2.2, "最低": 2.06, "周成交量": 2424139, "成交额": 516106351.0, "振幅": 6.39, "涨跌幅": -4.57, "涨跌额": -0.1, "换手率": 24.47}, {"日期": "2025-09-19 00:00:00", "股票代码": "300477", "开盘": 2.08, "收盘": 2.07, "最高": 2.21, "最低": 2.01, "周成交量": 3132161, "成交额": 653582990.0, "振幅": 9.57, "涨跌幅": -0.96, "涨跌额": -0.02, "换手率": 31.61}, {"日期": "2025-09-26 00:00:00", "股票代码": "300477", "开盘": 2.07, "收盘": 2.02, "最高": 2.14, "最低": 1.98, "周成交量": 2009512, "成交额": 411470220.0, "振幅": 7.73, "涨跌幅": -2.42, "涨跌额": -0.05, "换手率": 20.28}, {"日期": "2025-09-30 00:00:00", "股票代码": "300477", "开盘": 2.02, "收盘": 2.03, "最高": 2.07, "最低": 2.0, "周成交量": 682459, "成交额": 139321985.0, "振幅": 3.47, "涨跌幅": 0.5, "涨跌额": 0.01, "换手率": 6.89}, {"日期": "2025-10-10 00:00:00", "股票代码": "300477", "开盘": 2.05, "收盘": 2.01, "最高": 2.06, "最低": 2.0, "周成交量": 737164, "成交额": 148955890.0, "振幅": 2.96, "涨跌幅": -0.99, "涨跌额": -0.02, "换手率": 7.44}, {"日期": "2025-10-17 00:00:00", "股票代码": "300477", "开盘": 1.93, "收盘": 1.95, "最高": 2.0, "最低": 1.91, "周成交量": 1855777, "成交额": 364444024.0, "振幅": 4.48, "涨跌幅": -2.99, "涨跌额": -0.06, "换手率": 18.73}, {"日期": "2025-10-24 00:00:00", "股票代码": "300477", "开盘": 1.95, "收盘": 2.06, "最高": 2.12, "最低": 1.95, "周成交量": 1883989, "成交额": 379557029.0, "振幅": 8.72, "涨跌幅": 5.64, "涨跌额": 0.11, "换手率": 19.01}, {"日期": "2025-10-31 00:00:00", "股票代码": "300477", "开盘": 2.06, "收盘": 2.02, "最高": 2.07, "最低": 1.96, "周成交量": 1744975, "成交额": 350250375.0, "振幅": 5.34, "涨跌幅": -1.94, "涨跌额": -0.04, "换手率": 17.61}, {"日期": "2025-11-07 00:00:00", "股票代码": "300477", "开盘": 2.02, "收盘": 2.33, "最高": 2.48, "最低": 2.0, "周成交量": 4132236, "成交额": 914062796.0, "振幅": 23.76, "涨跌幅": 15.35, "涨跌额": 0.31, "换手率": 41.7}, {"日期": "2025-11-14 00:00:00", "股票代码": "300477", "开盘": 2.4, "收盘": 3.38, "最高": 3.38, "最低": 2.39, "周成交量": 8424943, "成交额": 2413465178.0, "振幅": 42.49, "涨跌幅": 45.06, "涨跌额": 1.05, "换手率": 85.03}, {"日期": "2025-11-21 00:00:00", "股票代码": "300477", "开盘": 3.5, "收盘": 3.74, "最高": 4.55, "最低": 3.27, "周成交量": 11381899, "成交额": 4436461425.0, "振幅": 37.87, "涨跌幅": 10.65, "涨跌额": 0.36, "换手率": 114.87}, {"日期": "2025-11-28 00:00:00", "股票代码": "300477", "开盘": 3.59, "收盘": 3.81, "最高": 4.14, "最低": 3.01, "周成交量": 9114793, "成交额": 3283289013.0, "振幅": 30.21, "涨跌幅": 1.87, "涨跌额": 0.07, "换手率": 91.99}, {"日期": "2025-12-05 00:00:00", "股票代码": "300477", "开盘": 3.86, "收盘": 3.22, "最高": 4.03, "最低": 3.16, "周成交量": 6050018, "成交额": 2112530868.0, "振幅": 22.83, "涨跌幅": -15.49, "涨跌额": -0.59, "换手率": 61.06}, {"日期": "2025-12-12 00:00:00", "股票代码": "300477", "开盘": 3.15, "收盘": 3.04, "最高": 3.52, "最低": 3.03, "周成交量": 5099878, "成交额": 1664785148.0, "振幅": 15.22, "涨跌幅": -5.59, "涨跌额": -0.18, "换手率": 51.47}, {"日期": "2025-12-19 00:00:00", "股票代码": "300477", "开盘": 3.03, "收盘": 3.02, "最高": 3.08, "最低": 2.76, "周成交量": 4293192, "成交额": 1262132349.0, "振幅": 10.53, "涨跌幅": -0.66, "涨跌额": -0.02, "换手率": 43.33}, {"日期": "2025-12-26 00:00:00", "股票代码": "300477", "开盘": 3.0, "收盘": 3.06, "最高": 3.19, "最低": 2.96, "周成交量": 3570912, "成交额": 1096222591.0, "振幅": 7.62, "涨跌幅": 1.32, "涨跌额": 0.04, "换手率": 36.04}, {"日期": "2025-12-31 00:00:00", "股票代码": "300477", "开盘": 3.04, "收盘": 2.62, "最高": 3.05, "最低": 2.59, "周成交量": 2305258, "成交额": 647851580.0, "振幅": 15.03, "涨跌幅": -14.38, "涨跌额": -0.44, "换手率": 23.27}, {"日期": "2026-01-09 00:00:00", "股票代码": "300477", "开盘": 2.67, "收盘": 2.7, "最高": 2.87, "最低": 2.56, "周成交量": 3168587, "成交额": 863440014.0, "振幅": 11.83, "涨跌幅": 3.05, "涨跌额": 0.08, "换手率": 31.98}, {"日期": "2026-01-16 00:00:00", "股票代码": "300477", "开盘": 2.73, "收盘": 3.3, "最高": 3.63, "最低": 2.6, "周成交量": 6426802, "成交额": 1961117515.0, "振幅": 38.15, "涨跌幅": 22.22, "涨跌额": 0.6, "换手率": 64.86}, {"日期": "2026-01-21 00:00:00", "股票代码": "300477", "开盘": 3.28, "收盘": 3.15, "最高": 3.61, "最低": 3.13, "周成交量": 3844544, "成交额": 1300699649.45, "振幅": 14.55, "涨跌幅": -4.55, "涨跌额": -0.15, "换手率": 38.8}]