[{"日期": "2024-01-26 00:00:00", "股票代码": "603179", "开盘": 45.4, "收盘": 40.9, "最高": 45.6, "最低": 40.51, "周成交量": 187641, "成交额": 800270009.0, "振幅": 11.23, "涨跌幅": -9.73, "涨跌额": -4.41, "换手率": 3.85}, {"日期": "2024-02-02 00:00:00", "股票代码": "603179", "开盘": 40.92, "收盘": 40.16, "最高": 41.76, "最低": 38.01, "周成交量": 238983, "成交额": 969089572.0, "振幅": 9.17, "涨跌幅": -1.81, "涨跌额": -0.74, "换手率": 4.9}, {"日期": "2024-02-08 00:00:00", "股票代码": "603179", "开盘": 39.83, "收盘": 46.5, "最高": 48.89, "最低": 38.4, "周成交量": 237738, "成交额": 1075181480.0, "振幅": 26.12, "涨跌幅": 15.79, "涨跌额": 6.34, "换手率": 4.88}, {"日期": "2024-02-23 00:00:00", "股票代码": "603179", "开盘": 46.5, "收盘": 43.87, "最高": 47.19, "最低": 41.01, "周成交量": 260873, "成交额": 1151164483.0, "振幅": 13.29, "涨跌幅": -5.66, "涨跌额": -2.63, "换手率": 5.35}, {"日期": "2024-03-01 00:00:00", "股票代码": "603179", "开盘": 44.58, "收盘": 42.9, "最高": 46.32, "最低": 41.74, "周成交量": 267765, "成交额": 1188464693.0, "振幅": 10.44, "涨跌幅": -2.21, "涨跌额": -0.97, "换手率": 5.49}, {"日期": "2024-03-08 00:00:00", "股票代码": "603179", "开盘": 42.83, "收盘": 41.26, "最高": 42.97, "最低": 39.76, "周成交量": 254146, "成交额": 1073717035.0, "振幅": 7.48, "涨跌幅": -3.82, "涨跌额": -1.64, "换手率": 5.22}, {"日期": "2024-03-15 00:00:00", "股票代码": "603179", "开盘": 41.17, "收盘": 44.1, "最高": 45.51, "最低": 41.17, "周成交量": 236771, "成交额": 1062649478.0, "振幅": 10.52, "涨跌幅": 6.88, "涨跌额": 2.84, "换手率": 4.86}, {"日期": "2024-03-22 00:00:00", "股票代码": "603179", "开盘": 44.73, "收盘": 41.14, "最高": 44.73, "最低": 40.76, "周成交量": 199925, "成交额": 868734579.0, "振幅": 9.0, "涨跌幅": -6.71, "涨跌额": -2.96, "换手率": 4.1}, {"日期": "2024-03-29 00:00:00", "股票代码": "603179", "开盘": 40.76, "收盘": 42.35, "最高": 43.85, "最低": 40.7, "周成交量": 251492, "成交额": 1081072578.0, "振幅": 7.66, "涨跌幅": 2.94, "涨跌额": 1.21, "换手率": 5.16}, {"日期": "2024-04-03 00:00:00", "股票代码": "603179", "开盘": 42.24, "收盘": 40.57, "最高": 43.9, "最低": 40.22, "周成交量": 165637, "成交额": 704592978.0, "振幅": 8.69, "涨跌幅": -4.2, "涨跌额": -1.78, "换手率": 3.4}, {"日期": "2024-04-12 00:00:00", "股票代码": "603179", "开盘": 38.22, "收盘": 40.4, "最高": 41.81, "最低": 38.22, "周成交量": 195318, "成交额": 805303320.0, "振幅": 8.85, "涨跌幅": -0.42, "涨跌额": -0.17, "换手率": 4.01}, {"日期": "2024-04-19 00:00:00", "股票代码": "603179", "开盘": 40.36, "收盘": 41.03, "最高": 42.18, "最低": 38.72, "周成交量": 272866, "成交额": 1120015004.0, "振幅": 8.56, "涨跌幅": 1.56, "涨跌额": 0.63, "换手率": 5.6}, {"日期": "2024-04-26 00:00:00", "股票代码": "603179", "开盘": 40.76, "收盘": 44.08, "最高": 44.34, "最低": 39.76, "周成交量": 201316, "成交额": 870210838.0, "振幅": 11.16, "涨跌幅": 7.43, "涨跌额": 3.05, "换手率": 4.13}, {"日期": "2024-04-30 00:00:00", "股票代码": "603179", "开盘": 45.5, "收盘": 45.77, "最高": 47.65, "最低": 45.4, "周成交量": 140233, "成交额": 659004722.0, "振幅": 5.1, "涨跌幅": 3.83, "涨跌额": 1.69, "换手率": 2.88}, {"日期": "2024-05-10 00:00:00", "股票代码": "603179", "开盘": 46.82, "收盘": 43.46, "最高": 46.82, "最低": 42.1, "周成交量": 215864, "成交额": 958279814.0, "振幅": 10.31, "涨跌幅": -5.05, "涨跌额": -2.31, "换手率": 4.43}, {"日期": "2024-05-17 00:00:00", "股票代码": "603179", "开盘": 43.0, "收盘": 44.75, "最高": 45.11, "最低": 42.6, "周成交量": 119802, "成交额": 536065905.0, "振幅": 5.78, "涨跌幅": 2.97, "涨跌额": 1.29, "换手率": 2.46}, {"日期": "2024-05-24 00:00:00", "股票代码": "603179", "开盘": 44.56, "收盘": 42.49, "最高": 45.59, "最低": 42.06, "周成交量": 133088, "成交额": 583630135.0, "振幅": 7.89, "涨跌幅": -5.05, "涨跌额": -2.26, "换手率": 2.73}, {"日期": "2024-05-31 00:00:00", "股票代码": "603179", "开盘": 42.53, "收盘": 43.05, "最高": 43.97, "最低": 41.43, "周成交量": 109487, "成交额": 471407935.0, "振幅": 5.98, "涨跌幅": 1.32, "涨跌额": 0.56, "换手率": 2.25}, {"日期": "2024-06-07 00:00:00", "股票代码": "603179", "开盘": 43.2, "收盘": 42.4, "最高": 43.87, "最低": 41.88, "周成交量": 146536, "成交额": 634795103.0, "振幅": 4.62, "涨跌幅": -1.51, "涨跌额": -0.65, "换手率": 3.01}, {"日期": "2024-06-14 00:00:00", "股票代码": "603179", "开盘": 42.05, "收盘": 43.1, "最高": 43.69, "最低": 41.17, "周成交量": 218761, "成交额": 936870988.0, "振幅": 5.94, "涨跌幅": 1.65, "涨跌额": 0.7, "换手率": 4.49}, {"日期": "2024-06-21 00:00:00", "股票代码": "603179", "开盘": 42.25, "收盘": 41.1, "最高": 44.6, "最低": 40.85, "周成交量": 206205, "成交额": 887468724.0, "振幅": 8.7, "涨跌幅": -4.64, "涨跌额": -2.0, "换手率": 4.23}, {"日期": "2024-06-28 00:00:00", "股票代码": "603179", "开盘": 40.7, "收盘": 38.94, "最高": 41.1, "最低": 38.47, "周成交量": 139543, "成交额": 557083229.0, "振幅": 6.4, "涨跌幅": -5.26, "涨跌额": -2.16, "换手率": 2.86}, {"日期": "2024-07-05 00:00:00", "股票代码": "603179", "开盘": 38.71, "收盘": 41.99, "最高": 43.57, "最低": 38.03, "周成交量": 225393, "成交额": 942851473.0, "振幅": 14.23, "涨跌幅": 7.83, "涨跌额": 3.05, "换手率": 4.63}, {"日期": "2024-07-12 00:00:00", "股票代码": "603179", "开盘": 41.4, "收盘": 43.98, "最高": 44.94, "最低": 41.23, "周成交量": 175082, "成交额": 765232049.0, "振幅": 8.84, "涨跌幅": 4.74, "涨跌额": 1.99, "换手率": 3.59}, {"日期": "2024-07-19 00:00:00", "股票代码": "603179", "开盘": 43.71, "收盘": 42.93, "最高": 45.27, "最低": 42.82, "周成交量": 125837, "成交额": 558174523.0, "振幅": 5.57, "涨跌幅": -2.39, "涨跌额": -1.05, "换手率": 2.58}, {"日期": "2024-07-26 00:00:00", "股票代码": "603179", "开盘": 43.0, "收盘": 41.05, "最高": 43.13, "最低": 39.38, "周成交量": 143675, "成交额": 597564366.0, "振幅": 8.74, "涨跌幅": -4.38, "涨跌额": -1.88, "换手率": 2.95}, {"日期": "2024-08-02 00:00:00", "股票代码": "603179", "开盘": 41.34, "收盘": 39.3, "最高": 41.4, "最低": 39.2, "周成交量": 134217, "成交额": 542080971.0, "振幅": 5.36, "涨跌幅": -4.26, "涨跌额": -1.75, "换手率": 2.75}, {"日期": "2024-08-09 00:00:00", "股票代码": "603179", "开盘": 39.35, "收盘": 38.4, "最高": 40.0, "最低": 38.26, "周成交量": 103241, "成交额": 404684425.0, "振幅": 4.43, "涨跌幅": -2.29, "涨跌额": -0.9, "换手率": 2.12}, {"日期": "2024-08-16 00:00:00", "股票代码": "603179", "开盘": 38.27, "收盘": 36.2, "最高": 38.32, "最低": 35.53, "周成交量": 139603, "成交额": 516382451.0, "振幅": 7.27, "涨跌幅": -5.73, "涨跌额": -2.2, "换手率": 2.86}, {"日期": "2024-08-23 00:00:00", "股票代码": "603179", "开盘": 36.11, "收盘": 33.67, "最高": 37.2, "最低": 33.4, "周成交量": 110608, "成交额": 389248511.0, "振幅": 10.5, "涨跌幅": -6.99, "涨跌额": -2.53, "换手率": 2.27}, {"日期": "2024-08-30 00:00:00", "股票代码": "603179", "开盘": 33.81, "收盘": 37.69, "最高": 38.11, "最低": 32.24, "周成交量": 167914, "成交额": 593693480.0, "振幅": 17.43, "涨跌幅": 11.94, "涨跌额": 4.02, "换手率": 3.45}, {"日期": "2024-09-06 00:00:00", "股票代码": "603179", "开盘": 37.7, "收盘": 38.64, "最高": 39.85, "最低": 36.11, "周成交量": 165350, "成交额": 635716381.0, "振幅": 9.92, "涨跌幅": 2.52, "涨跌额": 0.95, "换手率": 3.39}, {"日期": "2024-09-13 00:00:00", "股票代码": "603179", "开盘": 38.6, "收盘": 37.0, "最高": 39.25, "最低": 37.0, "周成交量": 115853, "成交额": 445160349.0, "振幅": 5.82, "涨跌幅": -4.24, "涨跌额": -1.64, "换手率": 2.38}, {"日期": "2024-09-20 00:00:00", "股票代码": "603179", "开盘": 37.15, "收盘": 38.94, "最高": 39.82, "最低": 36.67, "周成交量": 85063, "成交额": 330350023.0, "振幅": 8.51, "涨跌幅": 5.24, "涨跌额": 1.94, "换手率": 1.75}, {"日期": "2024-09-27 00:00:00", "股票代码": "603179", "开盘": 38.73, "收盘": 44.3, "最高": 44.4, "最低": 38.2, "周成交量": 172840, "成交额": 710008010.0, "振幅": 15.92, "涨跌幅": 13.76, "涨跌额": 5.36, "换手率": 3.55}, {"日期": "2024-09-30 00:00:00", "股票代码": "603179", "开盘": 45.7, "收盘": 48.76, "最高": 48.76, "最低": 45.7, "周成交量": 63712, "成交额": 309060987.0, "振幅": 6.91, "涨跌幅": 10.07, "涨跌额": 4.46, "换手率": 1.31}, {"日期": "2024-10-11 00:00:00", "股票代码": "603179", "开盘": 53.67, "收盘": 49.75, "最高": 55.68, "最低": 48.9, "周成交量": 327535, "成交额": 1714549063.0, "振幅": 13.9, "涨跌幅": 2.03, "涨跌额": 0.99, "换手率": 6.72}, {"日期": "2024-10-18 00:00:00", "股票代码": "603179", "开盘": 49.86, "收盘": 48.07, "最高": 50.11, "最低": 43.86, "周成交量": 267601, "成交额": 1256374585.0, "振幅": 12.56, "涨跌幅": -3.38, "涨跌额": -1.68, "换手率": 5.49}, {"日期": "2024-10-25 00:00:00", "股票代码": "603179", "开盘": 48.06, "收盘": 49.98, "最高": 53.2, "最低": 45.98, "周成交量": 333660, "成交额": 1635072900.0, "振幅": 15.02, "涨跌幅": 3.97, "涨跌额": 1.91, "换手率": 6.85}, {"日期": "2024-11-01 00:00:00", "股票代码": "603179", "开盘": 49.93, "收盘": 48.75, "最高": 51.59, "最低": 48.0, "周成交量": 212227, "成交额": 1060377928.0, "振幅": 7.18, "涨跌幅": -2.46, "涨跌额": -1.23, "换手率": 4.36}, {"日期": "2024-11-08 00:00:00", "股票代码": "603179", "开盘": 48.31, "收盘": 53.45, "最高": 54.2, "最低": 47.73, "周成交量": 344353, "成交额": 1764707832.0, "振幅": 13.27, "涨跌幅": 9.64, "涨跌额": 4.7, "换手率": 7.07}, {"日期": "2024-11-15 00:00:00", "股票代码": "603179", "开盘": 53.43, "收盘": 49.76, "最高": 58.2, "最低": 49.29, "周成交量": 327148, "成交额": 1779333194.0, "振幅": 16.67, "涨跌幅": -6.9, "涨跌额": -3.69, "换手率": 6.71}, {"日期": "2024-11-22 00:00:00", "股票代码": "603179", "开盘": 49.6, "收盘": 47.55, "最高": 51.05, "最低": 47.48, "周成交量": 233127, "成交额": 1152843870.0, "振幅": 7.17, "涨跌幅": -4.44, "涨跌额": -2.21, "换手率": 4.78}, {"日期": "2024-11-29 00:00:00", "股票代码": "603179", "开盘": 48.34, "收盘": 46.05, "最高": 49.2, "最低": 43.73, "周成交量": 276386, "成交额": 1266965322.0, "振幅": 11.5, "涨跌幅": -3.15, "涨跌额": -1.5, "换手率": 5.67}, {"日期": "2024-12-06 00:00:00", "股票代码": "603179", "开盘": 46.39, "收盘": 45.05, "最高": 47.9, "最低": 43.95, "周成交量": 216719, "成交额": 994532677.0, "振幅": 8.58, "涨跌幅": -2.17, "涨跌额": -1.0, "换手率": 4.45}, {"日期": "2024-12-13 00:00:00", "股票代码": "603179", "开盘": 45.47, "收盘": 46.2, "最高": 48.18, "最低": 44.74, "周成交量": 248439, "成交额": 1159508316.0, "振幅": 7.64, "涨跌幅": 2.55, "涨跌额": 1.15, "换手率": 5.1}, {"日期": "2024-12-20 00:00:00", "股票代码": "603179", "开盘": 46.06, "收盘": 45.71, "最高": 46.54, "最低": 44.36, "周成交量": 187299, "成交额": 858340984.0, "振幅": 4.72, "涨跌幅": -1.06, "涨跌额": -0.49, "换手率": 3.84}, {"日期": "2024-12-27 00:00:00", "股票代码": "603179", "开盘": 45.83, "收盘": 43.14, "最高": 45.89, "最低": 42.51, "周成交量": 204101, "成交额": 904159790.0, "振幅": 7.39, "涨跌幅": -5.62, "涨跌额": -2.57, "换手率": 4.19}, {"日期": "2025-01-03 00:00:00", "股票代码": "603179", "开盘": 43.1, "收盘": 42.25, "最高": 44.69, "最低": 41.91, "周成交量": 217458, "成交额": 943532395.0, "振幅": 6.44, "涨跌幅": -2.06, "涨跌额": -0.89, "换手率": 4.46}, {"日期": "2025-01-10 00:00:00", "股票代码": "603179", "开盘": 42.7, "收盘": 46.65, "最高": 48.35, "最低": 42.28, "周成交量": 447618, "成交额": 2080687772.0, "振幅": 14.37, "涨跌幅": 10.41, "涨跌额": 4.4, "换手率": 9.19}, {"日期": "2025-01-17 00:00:00", "股票代码": "603179", "开盘": 46.37, "收盘": 48.65, "最高": 49.3, "最低": 45.02, "周成交量": 261243, "成交额": 1251717154.0, "振幅": 9.17, "涨跌幅": 4.29, "涨跌额": 2.0, "换手率": 5.36}, {"日期": "2025-01-24 00:00:00", "股票代码": "603179", "开盘": 49.48, "收盘": 48.07, "最高": 51.08, "最低": 47.04, "周成交量": 276854, "成交额": 1352882273.0, "振幅": 8.3, "涨跌幅": -1.19, "涨跌额": -0.58, "换手率": 5.68}, {"日期": "2025-01-27 00:00:00", "股票代码": "603179", "开盘": 48.07, "收盘": 47.5, "最高": 48.39, "最低": 47.4, "周成交量": 27354, "成交额": 131835751.0, "振幅": 2.06, "涨跌幅": -1.19, "涨跌额": -0.57, "换手率": 0.56}, {"日期": "2025-02-07 00:00:00", "股票代码": "603179", "开盘": 47.5, "收盘": 51.68, "最高": 52.2, "最低": 46.3, "周成交量": 180412, "成交额": 905458249.0, "振幅": 12.42, "涨跌幅": 8.8, "涨跌额": 4.18, "换手率": 3.7}, {"日期": "2025-02-14 00:00:00", "股票代码": "603179", "开盘": 51.33, "收盘": 49.04, "最高": 51.67, "最低": 47.09, "周成交量": 305600, "成交额": 1509346552.0, "振幅": 8.86, "涨跌幅": -5.11, "涨跌额": -2.64, "换手率": 6.27}, {"日期": "2025-02-21 00:00:00", "股票代码": "603179", "开盘": 49.1, "收盘": 53.45, "最高": 55.6, "最低": 47.6, "周成交量": 422477, "成交额": 2186558107.0, "振幅": 16.31, "涨跌幅": 8.99, "涨跌额": 4.41, "换手率": 8.67}, {"日期": "2025-02-28 00:00:00", "股票代码": "603179", "开盘": 53.4, "收盘": 48.58, "最高": 56.58, "最低": 48.46, "周成交量": 483832, "成交额": 2567289130.0, "振幅": 15.19, "涨跌幅": -9.11, "涨跌额": -4.87, "换手率": 9.93}, {"日期": "2025-03-07 00:00:00", "股票代码": "603179", "开盘": 48.92, "收盘": 49.44, "最高": 50.9, "最低": 45.82, "周成交量": 559101, "成交额": 2702857803.0, "振幅": 10.46, "涨跌幅": 1.77, "涨跌额": 0.86, "换手率": 11.47}, {"日期": "2025-03-14 00:00:00", "股票代码": "603179", "开盘": 48.91, "收盘": 44.91, "最高": 49.75, "最低": 44.06, "周成交量": 532513, "成交额": 2459842076.0, "振幅": 11.51, "涨跌幅": -9.16, "涨跌额": -4.53, "换手率": 10.93}, {"日期": "2025-03-21 00:00:00", "股票代码": "603179", "开盘": 45.05, "收盘": 45.5, "最高": 47.22, "最低": 44.2, "周成交量": 313247, "成交额": 1445637710.0, "振幅": 6.72, "涨跌幅": 1.31, "涨跌额": 0.59, "换手率": 6.43}, {"日期": "2025-03-28 00:00:00", "股票代码": "603179", "开盘": 45.26, "收盘": 47.26, "最高": 47.8, "最低": 45.25, "周成交量": 250595, "成交额": 1183326375.0, "振幅": 5.6, "涨跌幅": 3.87, "涨跌额": 1.76, "换手率": 5.14}, {"日期": "2025-04-03 00:00:00", "股票代码": "603179", "开盘": 47.03, "收盘": 45.37, "最高": 47.62, "最低": 45.35, "周成交量": 124634, "成交额": 582702772.0, "振幅": 4.8, "涨跌幅": -4.0, "涨跌额": -1.89, "换手率": 2.56}, {"日期": "2025-04-11 00:00:00", "股票代码": "603179", "开盘": 41.61, "收盘": 43.45, "最高": 44.5, "最低": 37.2, "周成交量": 355514, "成交额": 1441309280.0, "振幅": 16.09, "涨跌幅": -4.23, "涨跌额": -1.92, "换手率": 7.3}, {"日期": "2025-04-18 00:00:00", "股票代码": "603179", "开盘": 43.2, "收盘": 39.46, "最高": 44.18, "最低": 39.25, "周成交量": 194379, "成交额": 811920109.0, "振幅": 11.35, "涨跌幅": -9.18, "涨跌额": -3.99, "换手率": 3.99}, {"日期": "2025-04-25 00:00:00", "股票代码": "603179", "开盘": 39.3, "收盘": 40.83, "最高": 42.22, "最低": 38.72, "周成交量": 197799, "成交额": 814875947.0, "振幅": 8.87, "涨跌幅": 3.47, "涨跌额": 1.37, "换手率": 4.06}, {"日期": "2025-04-30 00:00:00", "股票代码": "603179", "开盘": 40.9, "收盘": 39.97, "最高": 41.3, "最低": 38.4, "周成交量": 153956, "成交额": 616075966.0, "振幅": 7.1, "涨跌幅": -2.11, "涨跌额": -0.86, "换手率": 3.16}, {"日期": "2025-05-09 00:00:00", "股票代码": "603179", "开盘": 40.6, "收盘": 41.2, "最高": 43.95, "最低": 40.6, "周成交量": 271473, "成交额": 1156315023.0, "振幅": 8.38, "涨跌幅": 3.08, "涨跌额": 1.23, "换手率": 5.57}, {"日期": "2025-05-16 00:00:00", "股票代码": "603179", "开盘": 41.67, "收盘": 45.7, "最高": 47.04, "最低": 41.67, "周成交量": 332978, "成交额": 1493286500.0, "振幅": 13.03, "涨跌幅": 10.92, "涨跌额": 4.5, "换手率": 6.83}, {"日期": "2025-05-23 00:00:00", "股票代码": "603179", "开盘": 46.48, "收盘": 44.63, "最高": 46.68, "最低": 43.52, "周成交量": 217544, "成交额": 981502560.0, "振幅": 6.91, "涨跌幅": -2.34, "涨跌额": -1.07, "换手率": 4.46}, {"日期": "2025-05-30 00:00:00", "股票代码": "603179", "开盘": 44.57, "收盘": 46.95, "最高": 47.04, "最低": 42.65, "周成交量": 272259, "成交额": 1227074497.0, "振幅": 9.84, "涨跌幅": 5.2, "涨跌额": 2.32, "换手率": 5.59}, {"日期": "2025-06-06 00:00:00", "股票代码": "603179", "开盘": 46.71, "收盘": 45.94, "最高": 48.57, "最低": 44.13, "周成交量": 283213, "成交额": 1320121414.0, "振幅": 9.46, "涨跌幅": -2.15, "涨跌额": -1.01, "换手率": 5.81}, {"日期": "2025-06-13 00:00:00", "股票代码": "603179", "开盘": 45.59, "收盘": 46.5, "最高": 48.04, "最低": 43.91, "周成交量": 304458, "成交额": 1412124391.0, "振幅": 8.99, "涨跌幅": 1.22, "涨跌额": 0.56, "换手率": 6.25}, {"日期": "2025-06-20 00:00:00", "股票代码": "603179", "开盘": 46.38, "收盘": 44.88, "最高": 47.19, "最低": 44.7, "周成交量": 167132, "成交额": 766286539.0, "振幅": 5.35, "涨跌幅": -3.48, "涨跌额": -1.62, "换手率": 3.43}, {"日期": "2025-06-27 00:00:00", "股票代码": "603179", "开盘": 45.14, "收盘": 47.2, "最高": 49.0, "最低": 44.31, "周成交量": 251894, "成交额": 1186157931.0, "振幅": 10.45, "涨跌幅": 5.17, "涨跌额": 2.32, "换手率": 5.17}, {"日期": "2025-07-04 00:00:00", "股票代码": "603179", "开盘": 47.31, "收盘": 47.25, "最高": 47.65, "最低": 45.83, "周成交量": 156967, "成交额": 736644815.0, "振幅": 3.86, "涨跌幅": 0.11, "涨跌额": 0.05, "换手率": 3.22}, {"日期": "2025-07-11 00:00:00", "股票代码": "603179", "开盘": 47.13, "收盘": 44.08, "最高": 47.13, "最低": 43.35, "周成交量": 257652, "成交额": 1146248035.0, "振幅": 8.0, "涨跌幅": -6.71, "涨跌额": -3.17, "换手率": 5.29}, {"日期": "2025-07-18 00:00:00", "股票代码": "603179", "开盘": 44.0, "收盘": 45.92, "最高": 46.3, "最低": 43.65, "周成交量": 195585, "成交额": 879813443.0, "振幅": 6.01, "涨跌幅": 4.17, "涨跌额": 1.84, "换手率": 4.01}, {"日期": "2025-07-25 00:00:00", "股票代码": "603179", "开盘": 46.0, "收盘": 43.18, "最高": 46.1, "最低": 42.46, "周成交量": 261135, "成交额": 1151821910.0, "振幅": 7.93, "涨跌幅": -5.97, "涨跌额": -2.74, "换手率": 5.36}, {"日期": "2025-08-01 00:00:00", "股票代码": "603179", "开盘": 43.2, "收盘": 40.7, "最高": 43.37, "最低": 40.55, "周成交量": 316229, "成交额": 1309821498.0, "振幅": 6.53, "涨跌幅": -5.74, "涨跌额": -2.48, "换手率": 6.49}, {"日期": "2025-08-08 00:00:00", "股票代码": "603179", "开盘": 41.42, "收盘": 46.27, "最高": 49.6, "最低": 40.7, "周成交量": 947769, "成交额": 4386634878.0, "振幅": 21.87, "涨跌幅": 13.69, "涨跌额": 5.57, "换手率": 19.45}, {"日期": "2025-08-15 00:00:00", "股票代码": "603179", "开盘": 46.07, "收盘": 47.36, "最高": 49.1, "最低": 45.72, "周成交量": 570079, "成交额": 2706800232.0, "振幅": 7.3, "涨跌幅": 2.36, "涨跌额": 1.09, "换手率": 11.7}, {"日期": "2025-08-22 00:00:00", "股票代码": "603179", "开盘": 47.35, "收盘": 49.25, "最高": 49.88, "最低": 45.83, "周成交量": 645748, "成交额": 3091012386.0, "振幅": 8.55, "涨跌幅": 3.99, "涨跌额": 1.89, "换手率": 13.25}, {"日期": "2025-08-29 00:00:00", "股票代码": "603179", "开盘": 49.27, "收盘": 49.95, "最高": 52.0, "最低": 47.78, "周成交量": 558612, "成交额": 2792262167.0, "振幅": 8.57, "涨跌幅": 1.42, "涨跌额": 0.7, "换手率": 11.46}, {"日期": "2025-09-05 00:00:00", "股票代码": "603179", "开盘": 47.0, "收盘": 62.98, "最高": 64.88, "最低": 46.33, "周成交量": 1862401, "成交额": 10347111081.0, "振幅": 37.14, "涨跌幅": 26.09, "涨跌额": 13.03, "换手率": 38.22}, {"日期": "2025-09-12 00:00:00", "股票代码": "603179", "开盘": 62.95, "收盘": 69.78, "最高": 73.5, "最低": 62.02, "周成交量": 2083867, "成交额": 13946473816.0, "振幅": 18.23, "涨跌幅": 10.8, "涨跌额": 6.8, "换手率": 42.76}, {"日期": "2025-09-19 00:00:00", "股票代码": "603179", "开盘": 69.83, "收盘": 73.0, "最高": 85.98, "最低": 68.7, "周成交量": 1503836, "成交额": 11504759120.0, "振幅": 24.76, "涨跌幅": 4.61, "涨跌额": 3.22, "换手率": 30.86}, {"日期": "2025-09-26 00:00:00", "股票代码": "603179", "开盘": 75.48, "收盘": 76.5, "最高": 83.49, "最低": 75.26, "周成交量": 1104387, "成交额": 8763631877.0, "振幅": 11.27, "涨跌幅": 4.79, "涨跌额": 3.5, "换手率": 22.66}, {"日期": "2025-09-30 00:00:00", "股票代码": "603179", "开盘": 76.61, "收盘": 83.04, "最高": 84.15, "最低": 76.51, "周成交量": 436912, "成交额": 3595409384.0, "振幅": 9.99, "涨跌幅": 8.55, "涨跌额": 6.54, "换手率": 8.89}, {"日期": "2025-10-10 00:00:00", "股票代码": "603179", "开盘": 81.38, "收盘": 82.35, "最高": 87.56, "最低": 81.38, "周成交量": 378352, "成交额": 3202273577.0, "振幅": 7.44, "涨跌幅": -0.83, "涨跌额": -0.69, "换手率": 7.7}, {"日期": "2025-10-17 00:00:00", "股票代码": "603179", "开盘": 77.0, "收盘": 66.19, "最高": 79.88, "最低": 65.53, "周成交量": 1172476, "成交额": 8423832248.0, "振幅": 17.43, "涨跌幅": -19.62, "涨跌额": -16.16, "换手率": 23.85}, {"日期": "2025-10-24 00:00:00", "股票代码": "603179", "开盘": 67.75, "收盘": 73.59, "最高": 73.59, "最低": 66.0, "周成交量": 959566, "成交额": 6715297946.0, "振幅": 11.47, "涨跌幅": 11.18, "涨跌额": 7.4, "换手率": 19.52}, {"日期": "2025-10-31 00:00:00", "股票代码": "603179", "开盘": 76.0, "收盘": 77.06, "最高": 81.47, "最低": 73.59, "周成交量": 1176231, "成交额": 9037151361.0, "振幅": 10.71, "涨跌幅": 4.72, "涨跌额": 3.47, "换手率": 23.06}, {"日期": "2025-11-07 00:00:00", "股票代码": "603179", "开盘": 77.71, "收盘": 77.0, "最高": 81.99, "最低": 70.31, "周成交量": 1132495, "成交额": 8685703603.0, "振幅": 15.16, "涨跌幅": -0.08, "涨跌额": -0.06, "换手率": 22.2}, {"日期": "2025-11-14 00:00:00", "股票代码": "603179", "开盘": 75.08, "收盘": 65.18, "最高": 75.59, "最低": 62.1, "周成交量": 1035487, "成交额": 6903579974.0, "振幅": 17.52, "涨跌幅": -15.35, "涨跌额": -11.82, "换手率": 20.3}, {"日期": "2025-11-21 00:00:00", "股票代码": "603179", "开盘": 65.19, "收盘": 61.77, "最高": 66.96, "最低": 58.51, "周成交量": 667363, "成交额": 4137421501.0, "振幅": 12.96, "涨跌幅": -5.23, "涨跌额": -3.41, "换手率": 13.08}, {"日期": "2025-11-28 00:00:00", "股票代码": "603179", "开盘": 61.8, "收盘": 66.17, "最高": 68.68, "最低": 60.07, "周成交量": 726113, "成交额": 4739376035.0, "振幅": 13.94, "涨跌幅": 7.12, "涨跌额": 4.4, "换手率": 14.23}, {"日期": "2025-12-05 00:00:00", "股票代码": "603179", "开盘": 66.52, "收盘": 71.55, "最高": 72.42, "最低": 66.0, "周成交量": 735646, "成交额": 5122261695.0, "振幅": 9.7, "涨跌幅": 8.13, "涨跌额": 5.38, "换手率": 14.42}, {"日期": "2025-12-12 00:00:00", "股票代码": "603179", "开盘": 69.5, "收盘": 66.23, "最高": 70.6, "最低": 64.01, "周成交量": 752586, "成交额": 5033474073.0, "振幅": 9.21, "涨跌幅": -7.44, "涨跌额": -5.32, "换手率": 14.75}, {"日期": "2025-12-19 00:00:00", "股票代码": "603179", "开盘": 65.76, "收盘": 64.82, "最高": 67.19, "最低": 63.0, "周成交量": 384482, "成交额": 2507278210.0, "振幅": 6.33, "涨跌幅": -2.13, "涨跌额": -1.41, "换手率": 7.54}, {"日期": "2025-12-26 00:00:00", "股票代码": "603179", "开盘": 65.55, "收盘": 64.78, "最高": 67.42, "最低": 62.0, "周成交量": 538028, "成交额": 3472498056.0, "振幅": 8.36, "涨跌幅": -0.06, "涨跌额": -0.04, "换手率": 10.55}, {"日期": "2025-12-31 00:00:00", "股票代码": "603179", "开盘": 64.71, "收盘": 73.88, "最高": 74.99, "最低": 64.71, "周成交量": 577902, "成交额": 4127346477.0, "振幅": 15.87, "涨跌幅": 14.05, "涨跌额": 9.1, "换手率": 11.33}, {"日期": "2026-01-09 00:00:00", "股票代码": "603179", "开盘": 73.08, "收盘": 85.83, "最高": 85.83, "最低": 70.5, "周成交量": 1037970, "成交额": 8206439626.0, "振幅": 20.75, "涨跌幅": 16.17, "涨跌额": 11.95, "换手率": 20.35}, {"日期": "2026-01-16 00:00:00", "股票代码": "603179", "开盘": 89.36, "收盘": 99.77, "最高": 99.77, "最低": 82.36, "周成交量": 1004430, "成交额": 9166564557.0, "振幅": 20.28, "涨跌幅": 16.24, "涨跌额": 13.94, "换手率": 19.69}, {"日期": "2026-01-21 00:00:00", "股票代码": "603179", "开盘": 99.2, "收盘": 96.1, "最高": 108.41, "最低": 95.63, "周成交量": 758959, "成交额": 7659755361.0, "振幅": 12.81, "涨跌幅": -3.68, "涨跌额": -3.67, "换手率": 14.88}]